pgpasslib.py
pgpasslib-1.1.0.dist-info/DESCRIPTION.rst
pgpasslib-1.1.0.dist-info/METADATA
pgpasslib-1.1.0.dist-info/RECORD
pgpasslib-1.1.0.dist-info/WHEEL
pgpasslib-1.1.0.dist-info/metadata.json
pgpasslib-1.1.0.dist-info/top_level.txt
