Metadata-Version: 1.1
Name: pgpasslib
Version: 1.1.0
Summary: Library for getting passwords from PostgreSQL password files
Home-page: http://pgpasslib.readthedocs.io
Author: Gavin M. Roy
Author-email: gavinmroy@gmail.com
License: Copyright (c) 2014 Gavin M. Roy
